stdlogpj/LICENSE.txt
stdlogpj/__init__.py
stdlogpj/_version.py
stdlogpj/stdlog.py
stdlogpj-1.0.3.dist-info/METADATA
stdlogpj-1.0.3.dist-info/WHEEL
stdlogpj-1.0.3.dist-info/top_level.txt
stdlogpj-1.0.3.dist-info/zip-safe
stdlogpj-1.0.3.dist-info/RECORD
